db_utils_ge/__init__.py
db_utils_ge/config.py
db_utils_ge/fetcher.py
db_utils_ge-1.0.1.dist-info/LICENSE
db_utils_ge-1.0.1.dist-info/METADATA
db_utils_ge-1.0.1.dist-info/WHEEL
db_utils_ge-1.0.1.dist-info/top_level.txt
db_utils_ge-1.0.1.dist-info/RECORD
