Metadata-Version: 2.1
Name: db-utils-ge
Version: 1.0.1
Summary: DB access helper utilities
Home-page: https://github.build.ge.com/Fleet-Analytics-Europe/smart_mcr
Author: Oleg Osychenko
Author-email: oleg.osychenko@ge.com
License: MIT License
Platform: UNKNOWN
Classifier: Programming Language :: Python :: 3
Classifier: License :: OSI Approved :: MIT License
Classifier: Operating System :: Microsoft :: Windows
